{"version":"0.0.1","commands":{"scratcher:create":{"id":"scratcher:create","description":"Create a scratch org, install deps & pushes code","pluginName":"sfdx-plugin-scratcher","pluginType":"core","aliases":[],"examples":["$ sfdx scratcher:create\n        It will create the scratch orgs, install all of the dependancies, push the source code and assign the permssion of the app\n        "],"flags":{"json":{"name":"json","type":"boolean","description":"format output as json","required":false,"allowNo":false},"loglevel":{"name":"loglevel","type":"option","description":"logging level for this command invocation","required":false,"helpValue":"(trace|debug|info|warn|error|fatal)","options":["trace","debug","info","warn","error","fatal"]},"targetusername":{"name":"targetusername","type":"option","char":"u","description":"username or alias for the target org; overrides default target org","required":false},"targetdevhubusername":{"name":"targetdevhubusername","type":"option","char":"v","description":"username or alias for the dev hub org; overrides default dev hub org","required":false},"apiversion":{"name":"apiversion","type":"option","description":"override the api version used for api requests made by this command","required":false}},"args":[]}}}